ympush/__init__.py
ympush/getui/BatchImpl.py
ympush/getui/GtConfig.py
ympush/getui/RequestException.py
ympush/getui/__init__.py
ympush/getui/alias_demo.py
ympush/getui/demo.py
ympush/getui/igt_push.py
ympush/getui/google/__init__.py
ympush/getui/google/protobuf/__init__.py
ympush/getui/google/protobuf/any_pb2.py
ympush/getui/google/protobuf/any_test_pb2.py
ympush/getui/google/protobuf/api_pb2.py
ympush/getui/google/protobuf/descriptor.py
ympush/getui/google/protobuf/descriptor_database.py
ympush/getui/google/protobuf/descriptor_pb2.py
ympush/getui/google/protobuf/descriptor_pool.py
ympush/getui/google/protobuf/duration_pb2.py
ympush/getui/google/protobuf/empty_pb2.py
ympush/getui/google/protobuf/field_mask_pb2.py
ympush/getui/google/protobuf/json_format.py
ympush/getui/google/protobuf/map_proto2_unittest_pb2.py
ympush/getui/google/protobuf/map_unittest_pb2.py
ympush/getui/google/protobuf/message.py
ympush/getui/google/protobuf/message_factory.py
ympush/getui/google/protobuf/proto_builder.py
ympush/getui/google/protobuf/reflection.py
ympush/getui/google/protobuf/service.py
ympush/getui/google/protobuf/service_reflection.py
ympush/getui/google/protobuf/source_context_pb2.py
ympush/getui/google/protobuf/struct_pb2.py
ympush/getui/google/protobuf/symbol_database.py
ympush/getui/google/protobuf/test_messages_proto2_pb2.py
ympush/getui/google/protobuf/test_messages_proto3_pb2.py
ympush/getui/google/protobuf/text_encoding.py
ympush/getui/google/protobuf/text_format.py
ympush/getui/google/protobuf/timestamp_pb2.py
ympush/getui/google/protobuf/type_pb2.py
ympush/getui/google/protobuf/unittest_arena_pb2.py
ympush/getui/google/protobuf/unittest_custom_options_pb2.py
ympush/getui/google/protobuf/unittest_import_pb2.py
ympush/getui/google/protobuf/unittest_import_public_pb2.py
ympush/getui/google/protobuf/unittest_mset_pb2.py
ympush/getui/google/protobuf/unittest_mset_wire_format_pb2.py
ympush/getui/google/protobuf/unittest_no_arena_import_pb2.py
ympush-0.0.5.dist-info/LICENSE
ympush-0.0.5.dist-info/METADATA
ympush-0.0.5.dist-info/WHEEL
ympush-0.0.5.dist-info/top_level.txt
ympush-0.0.5.dist-info/RECORD
