Metadata-Version: 2.1
Name: ympush
Version: 0.0.5
Summary: ym push lib
Home-page: UNKNOWN
Author: ziggy
Author-email: zeddshiw@gmail.com
License: UNKNOWN
Platform: UNKNOWN
Classifier: Programming Language :: Python :: 3
Classifier: License :: OSI Approved :: MIT License
Classifier: Operating System :: OS Independent
Requires-Python: >=3.6
